[
  {
    "path": "GANSBERG KOEKELHOREN/DINGEN ZIJN GANSHOREN - FOTO'S - 2013 & 2020 & 2021/2048/1335278145-palbertphoto001.jpg",
    "folder": "GANSBERG KOEKELHOREN/DINGEN ZIJN GANSHOREN - FOTO'S - 2013 & 2020 & 2021/2048",
    "file": "1335278145-palbertphoto001.jpg",
    "mime": "image/png",
    "ext": "png",
    "uploadCareId": "4782be62-66e7-43f7-ac96-5bb37aa0aebc",
    "uploadCareInfo": {
      "datetime_removed": null,
      "datetime_stored": "2021-01-27T19:18:15.699383Z",
      "datetime_uploaded": "2021-01-27T19:18:15.518954Z",
      "image_info": {
        "color_mode": "RGB",
        "orientation": null,
        "format": "PNG",
        "sequence": false,
        "height": 573,
        "width": 800,
        "geo_location": null,
        "datetime_original": null,
        "dpi": null
      },
      "is_image": true,
      "is_ready": true,
      "mime_type": "image/jpeg",
      "original_file_url": "https://ucarecdn.com/4782be62-66e7-43f7-ac96-5bb37aa0aebc/1335278145palbertphoto001.jpg",
      "original_filename": "1335278145-palbertphoto001.jpg",
      "size": 1378045,
      "url": "https://api.uploadcare.com/files/4782be62-66e7-43f7-ac96-5bb37aa0aebc/",
      "uuid": "4782be62-66e7-43f7-ac96-5bb37aa0aebc",
      "source": null
    }
  },
  {
    "path": "GANSBERG KOEKELHOREN/DINGEN ZIJN GANSHOREN - FOTO'S - 2013 & 2020 & 2021/2048/200705030723_Vanderperren.jpg",
    "folder": "GANSBERG KOEKELHOREN/DINGEN ZIJN GANSHOREN - FOTO'S - 2013 & 2020 & 2021/2048",
    "file": "200705030723_Vanderperren.jpg",
    "mime": "image/jpeg",
    "ext": "jpg",
    "uploadCareId": "8cc727e8-5b3a-400d-aecd-a786e346a385",
    "uploadCareInfo": {
      "datetime_removed": null,
      "datetime_stored": "2021-01-27T19:18:16.492826Z",
      "datetime_uploaded": "2021-01-27T19:18:16.329094Z",
      "image_info": {
        "color_mode": "RGB",
        "orientation": null,
        "format": "JPEG",
        "sequence": false,
        "height": 315,
        "width": 450,
        "geo_location": null,
        "datetime_original": null,
        "dpi": null
      },
      "is_image": true,
      "is_ready": true,
      "mime_type": "image/jpeg",
      "original_file_url": "https://ucarecdn.com/8cc727e8-5b3a-400d-aecd-a786e346a385/200705030723_Vanderperren.jpg",
      "original_filename": "200705030723_Vanderperren.jpg",
      "size": 64925,
      "url": "https://api.uploadcare.com/files/8cc727e8-5b3a-400d-aecd-a786e346a385/",
      "uuid": "8cc727e8-5b3a-400d-aecd-a786e346a385",
      "source": null
    }
  },
  {
    "path": "GANSBERG KOEKELHOREN/DINGEN ZIJN GANSHOREN - FOTO'S - 2013 & 2020 & 2021/2048/air shots - gbatistini2.jpg",
    "folder": "GANSBERG KOEKELHOREN/DINGEN ZIJN GANSHOREN - FOTO'S - 2013 & 2020 & 2021/2048",
    "file": "air shots - gbatistini2.jpg",
    "mime": "image/jpeg",
    "ext": "jpg",
    "uploadCareId": "a3055eb9-ae98-4b1d-867b-f0d25d8ee5d9",
    "uploadCareInfo": {
      "datetime_removed": null,
      "datetime_stored": "2021-01-27T19:18:17.500649Z",
      "datetime_uploaded": "2021-01-27T19:18:17.351452Z",
      "image_info": {
        "color_mode": "RGB",
        "orientation": null,
        "format": "JPEG",
        "sequence": false,
        "height": 1024,
        "width": 982,
        "geo_location": null,
        "datetime_original": null,
        "dpi": [72, 72]
      },
      "is_image": true,
      "is_ready": true,
      "mime_type": "image/jpeg",
      "original_file_url": "https://ucarecdn.com/a3055eb9-ae98-4b1d-867b-f0d25d8ee5d9/airshotsgbatistini2.jpg",
      "original_filename": "air shots - gbatistini2.jpg",
      "size": 419375,
      "url": "https://api.uploadcare.com/files/a3055eb9-ae98-4b1d-867b-f0d25d8ee5d9/",
      "uuid": "a3055eb9-ae98-4b1d-867b-f0d25d8ee5d9",
      "source": null
    }
  },
  {
    "path": "GANSBERG KOEKELHOREN/DINGEN ZIJN GANSHOREN - FOTO'S - 2013 & 2020 & 2021/2048/air shots _ gbatistini.jpg",
    "folder": "GANSBERG KOEKELHOREN/DINGEN ZIJN GANSHOREN - FOTO'S - 2013 & 2020 & 2021/2048",
    "file": "air shots _ gbatistini.jpg",
    "mime": "image/jpeg",
    "ext": "jpg",
    "uploadCareId": "cf223544-8efe-4032-8da8-6b0fafd863cf",
    "uploadCareInfo": {
      "datetime_removed": null,
      "datetime_stored": "2021-01-27T19:18:18.789312Z",
      "datetime_uploaded": "2021-01-27T19:18:18.789312Z",
      "image_info": {
        "color_mode": "RGB",
        "orientation": null,
        "format": "JPEG",
        "sequence": false,
        "height": 1024,
        "width": 965,
        "geo_location": null,
        "datetime_original": null,
        "dpi": [350, 350]
      },
      "is_image": true,
      "is_ready": false,
      "mime_type": "image/jpeg",
      "original_file_url": null,
      "original_filename": "air shots _ gbatistini.jpg",
      "size": 731589,
      "url": "https://api.uploadcare.com/files/cf223544-8efe-4032-8da8-6b0fafd863cf/",
      "uuid": "cf223544-8efe-4032-8da8-6b0fafd863cf",
      "source": null
    }
  },
  {
    "path": "GANSBERG KOEKELHOREN/DINGEN ZIJN GANSHOREN - FOTO'S - 2013 & 2020 & 2021/2048/bos.jpg",
    "folder": "GANSBERG KOEKELHOREN/DINGEN ZIJN GANSHOREN - FOTO'S - 2013 & 2020 & 2021/2048",
    "file": "bos.jpg",
    "mime": "image/jpeg",
    "ext": "jpg",
    "uploadCareId": "74e027e0-50c8-4b17-bb33-9c6222aa270f",
    "uploadCareInfo": {
      "datetime_removed": null,
      "datetime_stored": "2021-01-27T19:18:20.093881Z",
      "datetime_uploaded": "2021-01-27T19:18:19.935124Z",
      "image_info": {
        "color_mode": "RGB",
        "orientation": null,
        "format": "JPEG",
        "sequence": false,
        "height": 768,
        "width": 1024,
        "geo_location": null,
        "datetime_original": null,
        "dpi": [72, 72]
      },
      "is_image": true,
      "is_ready": true,
      "mime_type": "image/jpeg",
      "original_file_url": "https://ucarecdn.com/74e027e0-50c8-4b17-bb33-9c6222aa270f/bos.jpg",
      "original_filename": "bos.jpg",
      "size": 722721,
      "url": "https://api.uploadcare.com/files/74e027e0-50c8-4b17-bb33-9c6222aa270f/",
      "uuid": "74e027e0-50c8-4b17-bb33-9c6222aa270f",
      "source": null
    }
  },
  {
    "path": "GANSBERG KOEKELHOREN/DINGEN ZIJN GANSHOREN - FOTO'S - 2013 & 2020 & 2021/2048/bosseler_flickr_8333398945_84062e8878_b.jpg",
    "folder": "GANSBERG KOEKELHOREN/DINGEN ZIJN GANSHOREN - FOTO'S - 2013 & 2020 & 2021/2048",
    "file": "bosseler_flickr_8333398945_84062e8878_b.jpg",
    "mime": "image/jpeg",
    "ext": "jpg",
    "uploadCareId": "72e61818-1445-4bc5-9314-59f2cf207f32",
    "uploadCareInfo": {
      "datetime_removed": null,
      "datetime_stored": "2021-01-27T19:18:21.037554Z",
      "datetime_uploaded": "2021-01-27T19:18:20.891474Z",
      "image_info": {
        "color_mode": "RGB",
        "orientation": null,
        "format": "JPEG",
        "sequence": false,
        "height": 682,
        "width": 1024,
        "geo_location": null,
        "datetime_original": null,
        "dpi": [100, 100]
      },
      "is_image": true,
      "is_ready": true,
      "mime_type": "image/jpeg",
      "original_file_url": "https://ucarecdn.com/72e61818-1445-4bc5-9314-59f2cf207f32/bosseler_flickr_8333398945_84062e8878_b.jpg",
      "original_filename": "bosseler_flickr_8333398945_84062e8878_b.jpg",
      "size": 317497,
      "url": "https://api.uploadcare.com/files/72e61818-1445-4bc5-9314-59f2cf207f32/",
      "uuid": "72e61818-1445-4bc5-9314-59f2cf207f32",
      "source": null
    }
  },
  {
    "path": "GANSBERG KOEKELHOREN/DINGEN ZIJN GANSHOREN - FOTO'S - 2013 & 2020 & 2021/2048/bosseler_flickr_8334435032_e9fd6fb5cf_b.jpg",
    "folder": "GANSBERG KOEKELHOREN/DINGEN ZIJN GANSHOREN - FOTO'S - 2013 & 2020 & 2021/2048",
    "file": "bosseler_flickr_8334435032_e9fd6fb5cf_b.jpg",
    "mime": "image/jpeg",
    "ext": "jpg",
    "uploadCareId": "b70b7780-d647-4101-b8a1-f873104afa25",
    "uploadCareInfo": {
      "datetime_removed": null,
      "datetime_stored": "2021-01-27T19:18:22.055290Z",
      "datetime_uploaded": "2021-01-27T19:18:21.865437Z",
      "image_info": {
        "color_mode": "RGB",
        "orientation": null,
        "format": "JPEG",
        "sequence": false,
        "height": 682,
        "width": 1024,
        "geo_location": null,
        "datetime_original": null,
        "dpi": [100, 100]
      },
      "is_image": true,
      "is_ready": true,
      "mime_type": "image/jpeg",
      "original_file_url": "https://ucarecdn.com/b70b7780-d647-4101-b8a1-f873104afa25/bosseler_flickr_8334435032_e9fd6fb5cf_b.jpg",
      "original_filename": "bosseler_flickr_8334435032_e9fd6fb5cf_b.jpg",
      "size": 378836,
      "url": "https://api.uploadcare.com/files/b70b7780-d647-4101-b8a1-f873104afa25/",
      "uuid": "b70b7780-d647-4101-b8a1-f873104afa25",
      "source": null
    }
  },
  {
    "path": "GANSBERG KOEKELHOREN/DINGEN ZIJN GANSHOREN - FOTO'S - 2013 & 2020 & 2021/2048/bosseler_flickr_8334445310_d8e521781a_b.jpg",
    "folder": "GANSBERG KOEKELHOREN/DINGEN ZIJN GANSHOREN - FOTO'S - 2013 & 2020 & 2021/2048",
    "file": "bosseler_flickr_8334445310_d8e521781a_b.jpg",
    "mime": "image/jpeg",
    "ext": "jpg",
    "uploadCareId": "3391043f-cc6d-4632-bb25-85c50c6626f6",
    "uploadCareInfo": {
      "datetime_removed": null,
      "datetime_stored": "2021-01-27T19:18:22.919567Z",
      "datetime_uploaded": "2021-01-27T19:18:22.817076Z",
      "image_info": {
        "color_mode": "RGB",
        "orientation": null,
        "format": "JPEG",
        "sequence": false,
        "height": 682,
        "width": 1024,
        "geo_location": null,
        "datetime_original": null,
        "dpi": [100, 100]
      },
      "is_image": true,
      "is_ready": true,
      "mime_type": "image/jpeg",
      "original_file_url": "https://ucarecdn.com/3391043f-cc6d-4632-bb25-85c50c6626f6/bosseler_flickr_8334445310_d8e521781a_b.jpg",
      "original_filename": "bosseler_flickr_8334445310_d8e521781a_b.jpg",
      "size": 349697,
      "url": "https://api.uploadcare.com/files/3391043f-cc6d-4632-bb25-85c50c6626f6/",
      "uuid": "3391043f-cc6d-4632-bb25-85c50c6626f6",
      "source": null
    }
  },
  {
    "path": "GANSBERG KOEKELHOREN/DINGEN ZIJN GANSHOREN - FOTO'S - 2013 & 2020 & 2021/2048/dorpsmeubilair_136435456_707819073497960_6634563461843034327_n.jpg",
    "folder": "GANSBERG KOEKELHOREN/DINGEN ZIJN GANSHOREN - FOTO'S - 2013 & 2020 & 2021/2048",
    "file": "dorpsmeubilair_136435456_707819073497960_6634563461843034327_n.jpg",
    "mime": "image/jpeg",
    "ext": "jpg",
    "uploadCareId": "c9e8d1c3-93fe-4de7-b637-5a572cd6c146",
    "uploadCareInfo": {
      "datetime_removed": null,
      "datetime_stored": "2021-01-27T19:18:23.812393Z",
      "datetime_uploaded": "2021-01-27T19:18:23.719148Z",
      "image_info": {
        "color_mode": "RGB",
        "orientation": null,
        "format": "JPEG",
        "sequence": false,
        "height": 563,
        "width": 750,
        "geo_location": null,
        "datetime_original": null,
        "dpi": null
      },
      "is_image": true,
      "is_ready": true,
      "mime_type": "image/jpeg",
      "original_file_url": "https://ucarecdn.com/c9e8d1c3-93fe-4de7-b637-5a572cd6c146/dorpsmeubilair_136435456_707819073497960_6634563461843034327_n.jpg",
      "original_filename": "dorpsmeubilair_136435456_707819073497960_6634563461843034327_n.jpg",
      "size": 103987,
      "url": "https://api.uploadcare.com/files/c9e8d1c3-93fe-4de7-b637-5a572cd6c146/",
      "uuid": "c9e8d1c3-93fe-4de7-b637-5a572cd6c146",
      "source": null
    }
  },
  {
    "path": "GANSBERG KOEKELHOREN/DINGEN ZIJN GANSHOREN - FOTO'S - 2013 & 2020 & 2021/2048/dorpsmeubilair_2004354411_b387c64bde_b.jpg",
    "folder": "GANSBERG KOEKELHOREN/DINGEN ZIJN GANSHOREN - FOTO'S - 2013 & 2020 & 2021/2048",
    "file": "dorpsmeubilair_2004354411_b387c64bde_b.jpg",
    "mime": "image/jpeg",
    "ext": "jpg",
    "uploadCareId": "942aa3a2-8b96-487b-aa58-996c5d751814",
    "uploadCareInfo": {
      "datetime_removed": null,
      "datetime_stored": "2021-01-27T19:18:24.955563Z",
      "datetime_uploaded": "2021-01-27T19:18:24.761381Z",
      "image_info": {
        "color_mode": "RGB",
        "orientation": null,
        "format": "JPEG",
        "sequence": false,
        "height": 768,
        "width": 1024,
        "geo_location": null,
        "datetime_original": null,
        "dpi": [72, 72]
      },
      "is_image": true,
      "is_ready": true,
      "mime_type": "image/jpeg",
      "original_file_url": "https://ucarecdn.com/942aa3a2-8b96-487b-aa58-996c5d751814/dorpsmeubilair_2004354411_b387c64bde_b.jpg",
      "original_filename": "dorpsmeubilair_2004354411_b387c64bde_b.jpg",
      "size": 443037,
      "url": "https://api.uploadcare.com/files/942aa3a2-8b96-487b-aa58-996c5d751814/",
      "uuid": "942aa3a2-8b96-487b-aa58-996c5d751814",
      "source": null
    }
  },
  {
    "path": "GANSBERG KOEKELHOREN/DINGEN ZIJN GANSHOREN - FOTO'S - 2013 & 2020 & 2021/2048/dorpsmeubilair_2359455568_63db7e330d_z.jpg",
    "folder": "GANSBERG KOEKELHOREN/DINGEN ZIJN GANSHOREN - FOTO'S - 2013 & 2020 & 2021/2048",
    "file": "dorpsmeubilair_2359455568_63db7e330d_z.jpg",
    "mime": "image/jpeg",
    "ext": "jpg",
    "uploadCareId": "98853ad5-3a8f-4b81-8e75-6396e062b096",
    "uploadCareInfo": {
      "datetime_removed": null,
      "datetime_stored": "2021-01-27T19:18:25.732796Z",
      "datetime_uploaded": "2021-01-27T19:18:25.570987Z",
      "image_info": {
        "color_mode": "RGB",
        "orientation": null,
        "format": "JPEG",
        "sequence": false,
        "height": 640,
        "width": 389,
        "geo_location": null,
        "datetime_original": null,
        "dpi": [72, 72]
      },
      "is_image": true,
      "is_ready": true,
      "mime_type": "image/jpeg",
      "original_file_url": "https://ucarecdn.com/98853ad5-3a8f-4b81-8e75-6396e062b096/dorpsmeubilair_2359455568_63db7e330d_z.jpg",
      "original_filename": "dorpsmeubilair_2359455568_63db7e330d_z.jpg",
      "size": 86220,
      "url": "https://api.uploadcare.com/files/98853ad5-3a8f-4b81-8e75-6396e062b096/",
      "uuid": "98853ad5-3a8f-4b81-8e75-6396e062b096",
      "source": null
    }
  },
  {
    "path": "GANSBERG KOEKELHOREN/DINGEN ZIJN GANSHOREN - FOTO'S - 2013 & 2020 & 2021/2048/fb_cafedessports_300874_133937480039235_452192584_n.jpg",
    "folder": "GANSBERG KOEKELHOREN/DINGEN ZIJN GANSHOREN - FOTO'S - 2013 & 2020 & 2021/2048",
    "file": "fb_cafedessports_300874_133937480039235_452192584_n.jpg",
    "mime": "image/jpeg",
    "ext": "jpg",
    "uploadCareId": "e470a7b8-1a7a-481b-a1db-63b2dd599f79",
    "uploadCareInfo": {
      "datetime_removed": null,
      "datetime_stored": "2021-01-27T19:18:26.636620Z",
      "datetime_uploaded": "2021-01-27T19:18:26.523483Z",
      "image_info": {
        "color_mode": "RGB",
        "orientation": null,
        "format": "JPEG",
        "sequence": false,
        "height": 655,
        "width": 960,
        "geo_location": null,
        "datetime_original": null,
        "dpi": null
      },
      "is_image": true,
      "is_ready": true,
      "mime_type": "image/jpeg",
      "original_file_url": "https://ucarecdn.com/e470a7b8-1a7a-481b-a1db-63b2dd599f79/fb_cafedessports_300874_133937480039235_452192584_n.jpg",
      "original_filename": "fb_cafedessports_300874_133937480039235_452192584_n.jpg",
      "size": 95603,
      "url": "https://api.uploadcare.com/files/e470a7b8-1a7a-481b-a1db-63b2dd599f79/",
      "uuid": "e470a7b8-1a7a-481b-a1db-63b2dd599f79",
      "source": null
    }
  },
  {
    "path": "GANSBERG KOEKELHOREN/DINGEN ZIJN GANSHOREN - FOTO'S - 2013 & 2020 & 2021/2048/fb_cafedessports_303995_144169545682695_1810270953_n.jpg",
    "folder": "GANSBERG KOEKELHOREN/DINGEN ZIJN GANSHOREN - FOTO'S - 2013 & 2020 & 2021/2048",
    "file": "fb_cafedessports_303995_144169545682695_1810270953_n.jpg",
    "mime": "image/jpeg",
    "ext": "jpg",
    "uploadCareId": "e7ff08a4-24df-48ec-b7f6-ebe36c22e755",
    "uploadCareInfo": {
      "datetime_removed": null,
      "datetime_stored": "2021-01-27T19:18:27.415881Z",
      "datetime_uploaded": "2021-01-27T19:18:27.272195Z",
      "image_info": {
        "color_mode": "RGB",
        "orientation": null,
        "format": "JPEG",
        "sequence": false,
        "height": 638,
        "width": 960,
        "geo_location": null,
        "datetime_original": null,
        "dpi": null
      },
      "is_image": true,
      "is_ready": true,
      "mime_type": "image/jpeg",
      "original_file_url": "https://ucarecdn.com/e7ff08a4-24df-48ec-b7f6-ebe36c22e755/fb_cafedessports_303995_144169545682695_1810270953_n.jpg",
      "original_filename": "fb_cafedessports_303995_144169545682695_1810270953_n.jpg",
      "size": 69805,
      "url": "https://api.uploadcare.com/files/e7ff08a4-24df-48ec-b7f6-ebe36c22e755/",
      "uuid": "e7ff08a4-24df-48ec-b7f6-ebe36c22e755",
      "source": null
    }
  },
  {
    "path": "GANSBERG KOEKELHOREN/DINGEN ZIJN GANSHOREN - FOTO'S - 2013 & 2020 & 2021/2048/fb_cafedessports_379494_159620557470927_1542300306_n.jpg",
    "folder": "GANSBERG KOEKELHOREN/DINGEN ZIJN GANSHOREN - FOTO'S - 2013 & 2020 & 2021/2048",
    "file": "fb_cafedessports_379494_159620557470927_1542300306_n.jpg",
    "mime": "image/jpeg",
    "ext": "jpg",
    "uploadCareId": "e34e83df-1503-40a4-9b45-7ba6ee175379",
    "uploadCareInfo": {
      "datetime_removed": null,
      "datetime_stored": "2021-01-27T19:18:28.133729Z",
      "datetime_uploaded": "2021-01-27T19:18:27.987571Z",
      "image_info": {
        "color_mode": "RGB",
        "orientation": null,
        "format": "JPEG",
        "sequence": false,
        "height": 717,
        "width": 960,
        "geo_location": null,
        "datetime_original": null,
        "dpi": null
      },
      "is_image": true,
      "is_ready": true,
      "mime_type": "image/jpeg",
      "original_file_url": "https://ucarecdn.com/e34e83df-1503-40a4-9b45-7ba6ee175379/fb_cafedessports_379494_159620557470927_1542300306_n.jpg",
      "original_filename": "fb_cafedessports_379494_159620557470927_1542300306_n.jpg",
      "size": 70989,
      "url": "https://api.uploadcare.com/files/e34e83df-1503-40a4-9b45-7ba6ee175379/",
      "uuid": "e34e83df-1503-40a4-9b45-7ba6ee175379",
      "source": null
    }
  },
  {
    "path": "GANSBERG KOEKELHOREN/DINGEN ZIJN GANSHOREN - FOTO'S - 2013 & 2020 & 2021/2048/fb_cafedessports_385037_150356041730712_540288350_n.jpg",
    "folder": "GANSBERG KOEKELHOREN/DINGEN ZIJN GANSHOREN - FOTO'S - 2013 & 2020 & 2021/2048",
    "file": "fb_cafedessports_385037_150356041730712_540288350_n.jpg",
    "mime": "image/jpeg",
    "ext": "jpg",
    "uploadCareId": "e3aa46af-3119-40fd-b066-67ab85721312",
    "uploadCareInfo": {
      "datetime_removed": null,
      "datetime_stored": "2021-01-27T19:18:28.949744Z",
      "datetime_uploaded": "2021-01-27T19:18:28.841258Z",
      "image_info": {
        "color_mode": "RGB",
        "orientation": null,
        "format": "JPEG",
        "sequence": false,
        "height": 960,
        "width": 717,
        "geo_location": null,
        "datetime_original": null,
        "dpi": null
      },
      "is_image": true,
      "is_ready": true,
      "mime_type": "image/jpeg",
      "original_file_url": "https://ucarecdn.com/e3aa46af-3119-40fd-b066-67ab85721312/fb_cafedessports_385037_150356041730712_540288350_n.jpg",
      "original_filename": "fb_cafedessports_385037_150356041730712_540288350_n.jpg",
      "size": 126682,
      "url": "https://api.uploadcare.com/files/e3aa46af-3119-40fd-b066-67ab85721312/",
      "uuid": "e3aa46af-3119-40fd-b066-67ab85721312",
      "source": null
    }
  },
  {
    "path": "GANSBERG KOEKELHOREN/DINGEN ZIJN GANSHOREN - FOTO'S - 2013 & 2020 & 2021/2048/fb_cafedessports_390324_159620617470921_2058286755_n.jpg",
    "folder": "GANSBERG KOEKELHOREN/DINGEN ZIJN GANSHOREN - FOTO'S - 2013 & 2020 & 2021/2048",
    "file": "fb_cafedessports_390324_159620617470921_2058286755_n.jpg",
    "mime": "image/jpeg",
    "ext": "jpg",
    "uploadCareId": "a09212b0-9046-4a08-bed2-26c7b5e70283",
    "uploadCareInfo": {
      "datetime_removed": null,
      "datetime_stored": "2021-01-27T19:18:29.692369Z",
      "datetime_uploaded": "2021-01-27T19:18:29.549154Z",
      "image_info": {
        "color_mode": "RGB",
        "orientation": null,
        "format": "JPEG",
        "sequence": false,
        "height": 717,
        "width": 960,
        "geo_location": null,
        "datetime_original": null,
        "dpi": null
      },
      "is_image": true,
      "is_ready": true,
      "mime_type": "image/jpeg",
      "original_file_url": "https://ucarecdn.com/a09212b0-9046-4a08-bed2-26c7b5e70283/fb_cafedessports_390324_159620617470921_2058286755_n.jpg",
      "original_filename": "fb_cafedessports_390324_159620617470921_2058286755_n.jpg",
      "size": 89647,
      "url": "https://api.uploadcare.com/files/a09212b0-9046-4a08-bed2-26c7b5e70283/",
      "uuid": "a09212b0-9046-4a08-bed2-26c7b5e70283",
      "source": null
    }
  },
  {
    "path": "GANSBERG KOEKELHOREN/DINGEN ZIJN GANSHOREN - FOTO'S - 2013 & 2020 & 2021/2048/kerkhof_4658880429_127192e4bf_b.jpg",
    "folder": "GANSBERG KOEKELHOREN/DINGEN ZIJN GANSHOREN - FOTO'S - 2013 & 2020 & 2021/2048",
    "file": "kerkhof_4658880429_127192e4bf_b.jpg",
    "mime": "image/jpeg",
    "ext": "jpg",
    "uploadCareId": "c3cccd67-d0e1-4e2d-858e-a4d65027c7ca",
    "uploadCareInfo": {
      "datetime_removed": null,
      "datetime_stored": "2021-01-27T19:18:30.846901Z",
      "datetime_uploaded": "2021-01-27T19:18:30.598269Z",
      "image_info": {
        "color_mode": "RGB",
        "orientation": null,
        "format": "JPEG",
        "sequence": false,
        "height": 680,
        "width": 1024,
        "geo_location": null,
        "datetime_original": null,
        "dpi": [72, 72]
      },
      "is_image": true,
      "is_ready": true,
      "mime_type": "image/jpeg",
      "original_file_url": "https://ucarecdn.com/c3cccd67-d0e1-4e2d-858e-a4d65027c7ca/kerkhof_4658880429_127192e4bf_b.jpg",
      "original_filename": "kerkhof_4658880429_127192e4bf_b.jpg",
      "size": 594017,
      "url": "https://api.uploadcare.com/files/c3cccd67-d0e1-4e2d-858e-a4d65027c7ca/",
      "uuid": "c3cccd67-d0e1-4e2d-858e-a4d65027c7ca",
      "source": null
    }
  },
  {
    "path": "GANSBERG KOEKELHOREN/DINGEN ZIJN GANSHOREN - FOTO'S - 2013 & 2020 & 2021/2048/la mia cucina_Knipsel.JPG",
    "folder": "GANSBERG KOEKELHOREN/DINGEN ZIJN GANSHOREN - FOTO'S - 2013 & 2020 & 2021/2048",
    "file": "la mia cucina_Knipsel.JPG",
    "mime": "image/jpeg",
    "ext": "jpg",
    "uploadCareId": "9fd23c11-d87b-4593-8f9e-4d817029df38",
    "uploadCareInfo": {
      "datetime_removed": null,
      "datetime_stored": "2021-01-27T19:18:31.676029Z",
      "datetime_uploaded": "2021-01-27T19:18:31.581666Z",
      "image_info": {
        "color_mode": "RGB",
        "orientation": null,
        "format": "JPEG",
        "sequence": false,
        "height": 847,
        "width": 854,
        "geo_location": null,
        "datetime_original": "2013-01-18T00:04:19",
        "dpi": [96, 96]
      },
      "is_image": true,
      "is_ready": true,
      "mime_type": "image/jpeg",
      "original_file_url": "https://ucarecdn.com/9fd23c11-d87b-4593-8f9e-4d817029df38/lamiacucina_Knipsel.JPG",
      "original_filename": "la mia cucina_Knipsel.JPG",
      "size": 134654,
      "url": "https://api.uploadcare.com/files/9fd23c11-d87b-4593-8f9e-4d817029df38/",
      "uuid": "9fd23c11-d87b-4593-8f9e-4d817029df38",
      "source": null
    }
  },
  {
    "path": "GANSBERG KOEKELHOREN/DINGEN ZIJN GANSHOREN - FOTO'S - 2013 & 2020 & 2021/2048/moestuinen_170547317_eeaa320a63_b.jpg",
    "folder": "GANSBERG KOEKELHOREN/DINGEN ZIJN GANSHOREN - FOTO'S - 2013 & 2020 & 2021/2048",
    "file": "moestuinen_170547317_eeaa320a63_b.jpg",
    "mime": "image/jpeg",
    "ext": "jpg",
    "uploadCareId": "d6dc4dd2-6a0b-4617-a2fe-408e33505947",
    "uploadCareInfo": {
      "datetime_removed": null,
      "datetime_stored": "2021-01-27T19:18:32.667678Z",
      "datetime_uploaded": "2021-01-27T19:18:32.508423Z",
      "image_info": {
        "color_mode": "RGB",
        "orientation": null,
        "format": "JPEG",
        "sequence": false,
        "height": 768,
        "width": 1024,
        "geo_location": null,
        "datetime_original": null,
        "dpi": [72, 72]
      },
      "is_image": true,
      "is_ready": true,
      "mime_type": "image/jpeg",
      "original_file_url": "https://ucarecdn.com/d6dc4dd2-6a0b-4617-a2fe-408e33505947/moestuinen_170547317_eeaa320a63_b.jpg",
      "original_filename": "moestuinen_170547317_eeaa320a63_b.jpg",
      "size": 363588,
      "url": "https://api.uploadcare.com/files/d6dc4dd2-6a0b-4617-a2fe-408e33505947/",
      "uuid": "d6dc4dd2-6a0b-4617-a2fe-408e33505947",
      "source": null
    }
  },
  {
    "path": "GANSBERG KOEKELHOREN/DINGEN ZIJN GANSHOREN - FOTO'S - 2013 & 2020 & 2021/2048/montana32_147235561.jpg",
    "folder": "GANSBERG KOEKELHOREN/DINGEN ZIJN GANSHOREN - FOTO'S - 2013 & 2020 & 2021/2048",
    "file": "montana32_147235561.jpg",
    "mime": "image/jpeg",
    "ext": "jpg",
    "uploadCareId": "3dc2b2a2-0268-4bb9-ab56-0f557394f6bf",
    "uploadCareInfo": {
      "datetime_removed": null,
      "datetime_stored": "2021-01-27T19:18:33.291179Z",
      "datetime_uploaded": "2021-01-27T19:18:33.194123Z",
      "image_info": {
        "color_mode": "RGB",
        "orientation": null,
        "format": "JPEG",
        "sequence": false,
        "height": 427,
        "width": 640,
        "geo_location": null,
        "datetime_original": null,
        "dpi": [96, 96]
      },
      "is_image": true,
      "is_ready": true,
      "mime_type": "image/jpeg",
      "original_file_url": "https://ucarecdn.com/3dc2b2a2-0268-4bb9-ab56-0f557394f6bf/montana32_147235561.jpg",
      "original_filename": "montana32_147235561.jpg",
      "size": 32994,
      "url": "https://api.uploadcare.com/files/3dc2b2a2-0268-4bb9-ab56-0f557394f6bf/",
      "uuid": "3dc2b2a2-0268-4bb9-ab56-0f557394f6bf",
      "source": null
    }
  },
  {
    "path": "GANSBERG KOEKELHOREN/DINGEN ZIJN GANSHOREN - FOTO'S - 2013 & 2020 & 2021/2048/montana32_147240255.jpg",
    "folder": "GANSBERG KOEKELHOREN/DINGEN ZIJN GANSHOREN - FOTO'S - 2013 & 2020 & 2021/2048",
    "file": "montana32_147240255.jpg",
    "mime": "image/jpeg",
    "ext": "jpg",
    "uploadCareId": "d0fb9532-5c44-40c1-8dc0-ce34466380f3",
    "uploadCareInfo": {
      "datetime_removed": null,
      "datetime_stored": "2021-01-27T19:18:35.015618Z",
      "datetime_uploaded": "2021-01-27T19:18:34.914158Z",
      "image_info": {
        "color_mode": "RGB",
        "orientation": null,
        "format": "JPEG",
        "sequence": false,
        "height": 500,
        "width": 333,
        "geo_location": null,
        "datetime_original": null,
        "dpi": [96, 96]
      },
      "is_image": true,
      "is_ready": true,
      "mime_type": "image/jpeg",
      "original_file_url": "https://ucarecdn.com/d0fb9532-5c44-40c1-8dc0-ce34466380f3/montana32_147240255.jpg",
      "original_filename": "montana32_147240255.jpg",
      "size": 24887,
      "url": "https://api.uploadcare.com/files/d0fb9532-5c44-40c1-8dc0-ce34466380f3/",
      "uuid": "d0fb9532-5c44-40c1-8dc0-ce34466380f3",
      "source": null
    }
  },
  {
    "path": "GANSBERG KOEKELHOREN/DINGEN ZIJN GANSHOREN - FOTO'S - 2013 & 2020 & 2021/2048/montana32_275110877.jpg",
    "folder": "GANSBERG KOEKELHOREN/DINGEN ZIJN GANSHOREN - FOTO'S - 2013 & 2020 & 2021/2048",
    "file": "montana32_275110877.jpg",
    "mime": "image/jpeg",
    "ext": "jpg",
    "uploadCareId": "6e3adf15-2125-499b-832c-92a2bd0cebca",
    "uploadCareInfo": {
      "datetime_removed": null,
      "datetime_stored": "2021-01-27T19:18:35.614430Z",
      "datetime_uploaded": "2021-01-27T19:18:35.521563Z",
      "image_info": {
        "color_mode": "RGB",
        "orientation": null,
        "format": "JPEG",
        "sequence": false,
        "height": 480,
        "width": 640,
        "geo_location": null,
        "datetime_original": null,
        "dpi": null
      },
      "is_image": true,
      "is_ready": true,
      "mime_type": "image/jpeg",
      "original_file_url": "https://ucarecdn.com/6e3adf15-2125-499b-832c-92a2bd0cebca/montana32_275110877.jpg",
      "original_filename": "montana32_275110877.jpg",
      "size": 36793,
      "url": "https://api.uploadcare.com/files/6e3adf15-2125-499b-832c-92a2bd0cebca/",
      "uuid": "6e3adf15-2125-499b-832c-92a2bd0cebca",
      "source": null
    }
  },
  {
    "path": "GANSBERG KOEKELHOREN/DINGEN ZIJN GANSHOREN - FOTO'S - 2013 & 2020 & 2021/2048/montana32_275119291.jpg",
    "folder": "GANSBERG KOEKELHOREN/DINGEN ZIJN GANSHOREN - FOTO'S - 2013 & 2020 & 2021/2048",
    "file": "montana32_275119291.jpg",
    "mime": "image/jpeg",
    "ext": "jpg",
    "uploadCareId": "0072815f-5ed1-49b4-800d-67f6e560c6b5",
    "uploadCareInfo": {
      "datetime_removed": null,
      "datetime_stored": "2021-01-27T19:18:36.220453Z",
      "datetime_uploaded": "2021-01-27T19:18:36.118348Z",
      "image_info": {
        "color_mode": "RGB",
        "orientation": null,
        "format": "JPEG",
        "sequence": false,
        "height": 480,
        "width": 640,
        "geo_location": null,
        "datetime_original": null,
        "dpi": null
      },
      "is_image": true,
      "is_ready": true,
      "mime_type": "image/jpeg",
      "original_file_url": "https://ucarecdn.com/0072815f-5ed1-49b4-800d-67f6e560c6b5/montana32_275119291.jpg",
      "original_filename": "montana32_275119291.jpg",
      "size": 36539,
      "url": "https://api.uploadcare.com/files/0072815f-5ed1-49b4-800d-67f6e560c6b5/",
      "uuid": "0072815f-5ed1-49b4-800d-67f6e560c6b5",
      "source": null
    }
  },
  {
    "path": "GANSBERG KOEKELHOREN/DINGEN ZIJN GANSHOREN - FOTO'S - 2013 & 2020 & 2021/2048/montana32_280759370.jpg",
    "folder": "GANSBERG KOEKELHOREN/DINGEN ZIJN GANSHOREN - FOTO'S - 2013 & 2020 & 2021/2048",
    "file": "montana32_280759370.jpg",
    "mime": "image/jpeg",
    "ext": "jpg",
    "uploadCareId": "72e266d7-06e4-4892-9329-e35cce431feb",
    "uploadCareInfo": {
      "datetime_removed": null,
      "datetime_stored": "2021-01-27T19:18:36.827837Z",
      "datetime_uploaded": "2021-01-27T19:18:36.735998Z",
      "image_info": {
        "color_mode": "RGB",
        "orientation": null,
        "format": "JPEG",
        "sequence": false,
        "height": 480,
        "width": 640,
        "geo_location": null,
        "datetime_original": null,
        "dpi": null
      },
      "is_image": true,
      "is_ready": true,
      "mime_type": "image/jpeg",
      "original_file_url": "https://ucarecdn.com/72e266d7-06e4-4892-9329-e35cce431feb/montana32_280759370.jpg",
      "original_filename": "montana32_280759370.jpg",
      "size": 31204,
      "url": "https://api.uploadcare.com/files/72e266d7-06e4-4892-9329-e35cce431feb/",
      "uuid": "72e266d7-06e4-4892-9329-e35cce431feb",
      "source": null
    }
  },
  {
    "path": "GANSBERG KOEKELHOREN/DINGEN ZIJN GANSHOREN - FOTO'S - 2013 & 2020 & 2021/2048/vdw-int_leds.JPG",
    "folder": "GANSBERG KOEKELHOREN/DINGEN ZIJN GANSHOREN - FOTO'S - 2013 & 2020 & 2021/2048",
    "file": "vdw-int_leds.JPG",
    "mime": "image/jpeg",
    "ext": "jpg",
    "uploadCareId": "7e8e9cea-2f79-4f03-81ad-4c6b650a80cc",
    "uploadCareInfo": {
      "datetime_removed": null,
      "datetime_stored": "2021-01-27T19:18:37.523086Z",
      "datetime_uploaded": "2021-01-27T19:18:37.372236Z",
      "image_info": {
        "color_mode": "RGB",
        "orientation": null,
        "format": "JPEG",
        "sequence": false,
        "height": 409,
        "width": 615,
        "geo_location": null,
        "datetime_original": "2013-01-20T17:50:48",
        "dpi": [96, 96]
      },
      "is_image": true,
      "is_ready": true,
      "mime_type": "image/jpeg",
      "original_file_url": "https://ucarecdn.com/7e8e9cea-2f79-4f03-81ad-4c6b650a80cc/vdwint_leds.JPG",
      "original_filename": "vdw-int_leds.JPG",
      "size": 35083,
      "url": "https://api.uploadcare.com/files/7e8e9cea-2f79-4f03-81ad-4c6b650a80cc/",
      "uuid": "7e8e9cea-2f79-4f03-81ad-4c6b650a80cc",
      "source": null
    }
  },
  {
    "path": "GANSBERG KOEKELHOREN/DINGEN ZIJN GANSHOREN - FOTO'S - 2013 & 2020 & 2021/2048/vdw-int_showroom.JPG",
    "folder": "GANSBERG KOEKELHOREN/DINGEN ZIJN GANSHOREN - FOTO'S - 2013 & 2020 & 2021/2048",
    "file": "vdw-int_showroom.JPG",
    "mime": "image/jpeg",
    "ext": "jpg",
    "uploadCareId": "eed15ec9-e07c-4d38-aece-a0cb8077b3d9",
    "uploadCareInfo": {
      "datetime_removed": null,
      "datetime_stored": "2021-01-27T19:18:38.220656Z",
      "datetime_uploaded": "2021-01-27T19:18:38.128193Z",
      "image_info": {
        "color_mode": "RGB",
        "orientation": null,
        "format": "JPEG",
        "sequence": false,
        "height": 411,
        "width": 616,
        "geo_location": null,
        "datetime_original": "2013-01-20T17:51:43",
        "dpi": [96, 96]
      },
      "is_image": true,
      "is_ready": true,
      "mime_type": "image/jpeg",
      "original_file_url": "https://ucarecdn.com/eed15ec9-e07c-4d38-aece-a0cb8077b3d9/vdwint_showroom.JPG",
      "original_filename": "vdw-int_showroom.JPG",
      "size": 88134,
      "url": "https://api.uploadcare.com/files/eed15ec9-e07c-4d38-aece-a0cb8077b3d9/",
      "uuid": "eed15ec9-e07c-4d38-aece-a0cb8077b3d9",
      "source": null
    }
  }
]
